[
  {
    "id": "debug",
    "type": "checkbox",
    "label": {
      "en": "Enable more logging (for diagnostics reports)"
    },
    "hint": { "en": "Turn this on to log extra details for troubleshooting received values for this device." },
    "value": false
  },
  {
    "id": "src",
    "type": "label",
    "label": {
      "en": "Source label of UDP messages"
    },
    "value": ""
  },
  {
    "id": "port",
    "type": "label",
    "label": {
      "en": "UDP Port number"
    },
    "value": "30000",
    "hint": { "en": "This Homey App requires all batteries listed to port 30000" }
  },
  {
    "id": "model",
    "type": "label",
    "label": {
      "en": "Model name"
    },
    "value": "(model)"
  }
]